dicetray/__init__.py
dicetray/lexer.py
dicetray/parser.py
dicetray-2.1.1.dist-info/WHEEL
dicetray-2.1.1.dist-info/METADATA
dicetray-2.1.1.dist-info/RECORD
