Metadata-Version: 2.1
Name: dicetray
Version: 2.1.1
Summary: Tabletop RPG Dice roller
Home-page: https://github.com/gtmanfred/dicetray.git
License: Apache-2.0
Author: Daniel Wallace
Author-email: danielwallace@gtmanfred.com
Requires-Python: >=3.8,<4.0
Classifier: Development Status :: 4 - Beta
Classifier: License :: OSI Approved :: Apache Software License
Classifier: Operating System :: OS Independent
Classifier: Programming Language :: Python :: 3
Classifier: Programming Language :: Python :: 3.8
Classifier: Programming Language :: Python :: 3.9
Classifier: Topic :: Software Development :: Libraries :: Python Modules
Requires-Dist: sly (>=0.4,<0.5)
Project-URL: Repository, https://github.com/gtmanfred/dicetray.git
